frilement/__init__.py
frilement/enums/__init__.py
frilement/enums/fileFormat.py
frilement/models/__init__.py
frilement/models/config/__init__.py
frilement/models/config/frilementConfig.py
frilement/models/pool/__init__.py
frilement/models/pool/frilementPool.py
frilement/services/__init__.py
frilement/services/IO/__init__.py
frilement/services/IO/fileService.py
frilement/services/frilement/__init__.py
frilement/services/frilement/frilementService.py
frilement-1.0.1.dist-info/LICENSE
frilement-1.0.1.dist-info/METADATA
frilement-1.0.1.dist-info/WHEEL
frilement-1.0.1.dist-info/top_level.txt
frilement-1.0.1.dist-info/RECORD
