Metadata-Version: 2.1
Name: frilement
Version: 1.0.1
Home-page: https://github.com/Neyzv/Frilement
Author: Neyzu
License-File: LICENSE
Requires-Dist: streamingpool
Requires-Dist: pyarrow
Requires-Dist: dask[dataframe]
